LICENSE
MANIFEST.in
README.md
pyproject.toml
setup.py
test.sh
mercury/version.py
mercury/graph/__init__.py
mercury/graph/create_tutorials.py
mercury/graph/core/__init__.py
mercury/graph/core/_njit.py
mercury/graph/core/base.py
mercury/graph/core/graph.py
mercury/graph/core/spark_interface.py
mercury/graph/embeddings/__init__.py
mercury/graph/embeddings/embeddings.py
mercury/graph/embeddings/graphembeddings.py
mercury/graph/embeddings/spark_node2vec.py
mercury/graph/frontend/moebius.css
mercury/graph/frontend/moebius.js
mercury/graph/frontend/moebius.svg.html
mercury/graph/ml/__init__.py
mercury/graph/ml/graph_features.py
mercury/graph/ml/louvain.py
mercury/graph/ml/spark_randomwalker.py
mercury/graph/ml/spark_spreadactivation.py
mercury/graph/ml/spectral.py
mercury/graph/ml/transition.py
mercury/graph/tutorials/mercury-graph-tutorial-banksim-nospark.ipynb
mercury/graph/tutorials/mercury-graph-tutorial-banksim.ipynb
mercury/graph/tutorials/mercury-graph-tutorial-fifa-nospark.ipynb
mercury/graph/tutorials/mercury-graph-tutorial-fifa.ipynb
mercury/graph/tutorials/mercury-graph-tutorial-graph-features.ipynb
mercury/graph/tutorials/moebius_demo.ipynb
mercury/graph/tutorials/data/chamberi_aristas.csv
mercury/graph/tutorials/data/chamberi_nodos.csv
mercury/graph/tutorials/data/fifa17_edges.csv
mercury/graph/tutorials/data/fifa17_nodes.csv
mercury/graph/tutorials/data/un_comtrade_2016_names.csv
mercury/graph/tutorials/data/un_comtrade_2016_sample.csv
mercury/graph/viz/__init__.py
mercury/graph/viz/moebius.py
mercury_graph.egg-info/PKG-INFO
mercury_graph.egg-info/SOURCES.txt
mercury_graph.egg-info/dependency_links.txt
mercury_graph.egg-info/requires.txt
mercury_graph.egg-info/top_level.txt