Metadata-Version: 2.1
Name: mercury-graph
Version: 3.2.6
Summary: mercury-graph offers graph analytics capabilities with a technology-agnostic API
Author-email: Mercury Team <mercury.group@bbva.com>
License:                                  Apache License
Keywords: graph,embedding,graph embedding,graph exploration,graph metrics,graph visualization
Classifier: Programming Language :: Python :: 3
Classifier: License :: OSI Approved :: Apache Software License
Classifier: Operating System :: OS Independent
Requires-Python: >=3.8
Provides-Extra: dev
Provides-Extra: doc
License-File: LICENSE
